libname/CustomEncoder.py
libname/__init__.py
CustomEncoder-0.0.1.dist-info/LICENSE
CustomEncoder-0.0.1.dist-info/METADATA
CustomEncoder-0.0.1.dist-info/WHEEL
CustomEncoder-0.0.1.dist-info/top_level.txt
CustomEncoder-0.0.1.dist-info/RECORD
