Metadata-Version: 2.1
Name: CustomEncoder
Version: 0.0.1
Summary: A custom LabelEncoder implementation
Author: Tanmay Chakraborty
Author-email: chakrabortytanmay326@gmail.com
License: UNKNOWN
Keywords: python,encoder,machine-learning
Platform: UNKNOWN
Classifier: Development Status :: 1 - Planning
Classifier: Intended Audience :: Developers
Classifier: Programming Language :: Python :: 3
Classifier: Operating System :: Microsoft :: Windows
License-File: LICENSE
Requires-Dist: pandas
Requires-Dist: numpy
